.gitignore
CHANGES.txt
LICENSE.txt
MANIFEST.in
README.rst
setup.py
storagedef/__init__.py
storagedef/exceptions.py
storagedef/interfaces.py
storagedef/session.py
storagedef.egg-info/PKG-INFO
storagedef.egg-info/SOURCES.txt
storagedef.egg-info/dependency_links.txt
storagedef.egg-info/not-zip-safe
storagedef.egg-info/requires.txt
storagedef.egg-info/top_level.txt
storagedef/engines/__init__.py
storagedef/engines/localmemory.py
storagedef/engines/s3.py
storagedef/engines/tests/__init__.py
storagedef/engines/tests/test_localmemory.py
storagedef/engines/tests/test_s3.py
storagedef/tests/__init__.py
storagedef/tests/test_session.py