Metadata-Version: 1.1
Name: storagedef
Version: 0.1
Summary: Abstract storage interfaces
Home-page: https://github.com/gjo/storagedef
Author: OCHIAI, Gouji
Author-email: gjo.ext@gmail.com
License: BSD
Platform: UNKNOWN
Classifier: Framework :: Paste
Classifier: Framework :: Pyramid
Classifier: License :: OSI Approved :: BSD License
Classifier: Programming Language :: Python
Classifier: Programming Language :: Python :: 3.4
